smop/__init__.py
smop/backend.py
smop/callgraph.py
smop/lexer.py
smop/libsmop.py
smop/main.py
smop/mygraphviz.py
smop/node.py
smop/options.py
smop/parse.py
smop/recipes.py
smop/resolve.py
smop/rewrite.py
smop/test_lexer.py
smop/test_matlabarray.py
smop/test_parse.py
smop/test_primes.py
smop/test_solver.py
smop/version.py
smop3-0.41b0.dist-info/LICENSE.MIT
smop3-0.41b0.dist-info/METADATA
smop3-0.41b0.dist-info/WHEEL
smop3-0.41b0.dist-info/entry_points.txt
smop3-0.41b0.dist-info/top_level.txt
smop3-0.41b0.dist-info/RECORD
