Metadata-Version: 2.1
Name: smop3
Version: 0.41b0
Summary: Matlab to Python converter. Community maintained fork for Python 3.
Home-page: https://github.com/victorlei/smop
Author: Victor Leikehman
Author-email: victorlei@gmail.com
License: MIT
Download-URL: https://github.com/victorlei/smop
Keywords: convert translate matlab octave python
Platform: UNKNOWN
License-File: LICENSE.MIT
Requires-Dist: pytest
Requires-Dist: ply
Requires-Dist: numpy
Requires-Dist: scipy
Requires-Dist: networkx
